qbittorrent_api-2025.11.0.dist-info/licenses/LICENSE
qbittorrentapi/__init__.py
qbittorrentapi/_attrdict.py
qbittorrentapi/_version_support.py
qbittorrentapi/app.py
qbittorrentapi/auth.py
qbittorrentapi/client.py
qbittorrentapi/definitions.py
qbittorrentapi/exceptions.py
qbittorrentapi/log.py
qbittorrentapi/py.typed
qbittorrentapi/request.py
qbittorrentapi/rss.py
qbittorrentapi/search.py
qbittorrentapi/sync.py
qbittorrentapi/torrentcreator.py
qbittorrentapi/torrents.py
qbittorrentapi/transfer.py
qbittorrent_api-2025.11.0.dist-info/METADATA
qbittorrent_api-2025.11.0.dist-info/WHEEL
qbittorrent_api-2025.11.0.dist-info/top_level.txt
qbittorrent_api-2025.11.0.dist-info/RECORD
