Metadata-Version: 2.4
Name: qbittorrent-api
Version: 2025.11.0
Summary: Python client for qBittorrent v4.1+ Web API.
Author: Russell Martin
Maintainer: Russell Martin
License-Expression: MIT
Project-URL: Homepage, https://github.com/rmartin16/qbittorrent-api
Project-URL: Documentation, https://qbittorrent-api.readthedocs.io/
Project-URL: API Reference, https://qbittorrent-api.readthedocs.io/en/latest/api.html
Project-URL: Source, https://github.com/rmartin16/qbittorrent-api
Keywords: python,qbittorrent,api,client,torrent,torrents,webui,web
Classifier: Development Status :: 5 - Production/Stable
Classifier: Intended Audience :: Developers
Classifier: Operating System :: OS Independent
Classifier: Environment :: Console
Classifier: Programming Language :: Python :: 3
Classifier: Programming Language :: Python :: 3.9
Classifier: Programming Language :: Python :: 3.10
Classifier: Programming Language :: Python :: 3.11
Classifier: Programming Language :: Python :: 3.12
Classifier: Programming Language :: Python :: 3.13
Classifier: Programming Language :: Python :: 3.14
Classifier: Programming Language :: Python :: 3 :: Only
Classifier: Programming Language :: Python :: Implementation :: CPython
Classifier: Topic :: Utilities
Classifier: Topic :: Communications :: File Sharing
Requires-Python: >=3.9
License-File: LICENSE
Requires-Dist: packaging
Requires-Dist: requests>=2.16.0
Requires-Dist: urllib3>=1.24.2
Provides-Extra: dev
Requires-Dist: build==1.3.0; extra == "dev"
Requires-Dist: coverage[toml]==7.10.7; extra == "dev"
Requires-Dist: mypy==1.18.2; extra == "dev"
Requires-Dist: pre-commit==4.3.0; extra == "dev"
Requires-Dist: pytest==8.4.2; extra == "dev"
Requires-Dist: tox==4.30.3; extra == "dev"
Requires-Dist: twine==6.2.0; extra == "dev"
Requires-Dist: types-requests==2.32.4.20250913; extra == "dev"
Provides-Extra: docs
Requires-Dist: furo==2025.9.25; extra == "docs"
Requires-Dist: sphinx==8.2.1; extra == "docs"
Requires-Dist: sphinx-autobuild==2024.10.3; extra == "docs"
Requires-Dist: sphinx-copybutton==0.5.2; extra == "docs"
Requires-Dist: sphinxcontrib-spelling==8.0.1; extra == "docs"
Requires-Dist: sphinx-autodoc-typehints==3.1.0; extra == "docs"
Dynamic: license-file
